tixelbox/__init__.py
tixelbox/audio.py
tixelbox/face_detection.py
tixelbox/object_detection.py
tixelbox/optical_flow.py
tixelbox/pose_detection.py
tixelbox/prelude.py
tixelbox/shot_detection.py
tixelbox/tf_vis_utils.py
tixelbox/video.py
tixelbox/vis.py
tixelbox/kernels/__init__.py
tixelbox/kernels/bbox_draw_kernel.py
tixelbox/kernels/bbox_nms_kernel.py
tixelbox/kernels/flow_draw_kernel.py
tixelbox/kernels/obj_detect_kernel.py
tixelbox/kernels/pose_draw_kernel.py
tixelbox-0.1.3.dist-info/DESCRIPTION.rst
tixelbox-0.1.3.dist-info/METADATA
tixelbox-0.1.3.dist-info/RECORD
tixelbox-0.1.3.dist-info/WHEEL
tixelbox-0.1.3.dist-info/metadata.json
tixelbox-0.1.3.dist-info/top_level.txt
