Metadata-Version: 2.0
Name: tixelbox
Version: 0.1.3
Summary: Video analytics toolkit
Home-page: http://github.com/scanner-research/tixelbox
Author: Alex Poms and Will Crichton
Author-email: apoms@cs.stanford.edu
License: Apache 2.0
Platform: UNKNOWN
Requires-Dist: numpy
Requires-Dist: requests
Requires-Dist: requests
Requires-Dist: scipy
